{
	"name": "DelimitedText1",
	"properties": {
		"linkedServiceName": {
			"referenceName": "Link_test_Blob",
			"type": "LinkedServiceReference"
		},
		"annotations": [],
		"type": "DelimitedText",
		"typeProperties": {
			"location": {
				"type": "AzureBlobStorageLocation",
				"fileName": "cars.csv",
				"container": "container-test"
			},
			"columnDelimiter": ",",
			"escapeChar": "\\",
			"firstRowAsHeader": true,
			"quoteChar": "\""
		},
		"schema": [
			{
				"name": "Make",
				"type": "String"
			},
			{
				"name": "Model",
				"type": "String"
			},
			{
				"name": "Type",
				"type": "String"
			},
			{
				"name": "Origin",
				"type": "String"
			},
			{
				"name": "DriveTrain",
				"type": "String"
			},
			{
				"name": "Length",
				"type": "String"
			}
		]
	},
	"type": "Microsoft.DataFactory/factories/datasets"
}